runningman/__init__.py
runningman/client.py
runningman/manager.py
runningman/status.py
runningman/version.py
runningman/wrappers.py
runningman/cli/__init__.py
runningman/cli/cmd_service.py
runningman/cli/cmd_trigger.py
runningman/cli/commands.py
runningman/providers/__init__.py
runningman/providers/expired_files.py
runningman/providers/match_file_trees.py
runningman/providers/new_files.py
runningman/providers/provider.py
runningman/services/__init__.py
runningman/services/service.py
runningman/triggers/__init__.py
runningman/triggers/cron.py
runningman/triggers/network.py
runningman/triggers/new_files.py
runningman/triggers/timed.py
runningman/triggers/trigger.py
station_runtime-0.2.1.dist-info/LICENSE
station_runtime-0.2.1.dist-info/METADATA
station_runtime-0.2.1.dist-info/WHEEL
station_runtime-0.2.1.dist-info/entry_points.txt
station_runtime-0.2.1.dist-info/top_level.txt
station_runtime-0.2.1.dist-info/RECORD
