Metadata-Version: 2.1
Name: station-runtime
Version: 0.2.1
Summary: Runtime Manager, i.e. a running-man(ager), for setting up a set of service like processes that are asynchronously managed by triggers and fed data trough queues.
Author-email: Daniel Kastinen <daniel.kastinen@irf.se>
Maintainer-email: Daniel Kastinen <daniel.kastinen@irf.se>
License: GNU GENERAL PUBLIC LICENSE
Project-URL: Documentation, https://danielk.developer.irf.se/runningman/
Project-URL: Repository, https://github.com/danielk333/runningman
Classifier: Programming Language :: Python :: 3
Requires-Python: >=3.7
License-File: LICENSE
Requires-Dist: watchdog
Requires-Dist: croniter
Requires-Dist: pyzmq
Provides-Extra: develop
Requires-Dist: pytest ; extra == 'develop'
Requires-Dist: flake8 ; extra == 'develop'
Requires-Dist: wheel ; extra == 'develop'
Requires-Dist: build ; extra == 'develop'
Requires-Dist: twine ; extra == 'develop'
Requires-Dist: numpydoc ; extra == 'develop'
Requires-Dist: black ; extra == 'develop'
Requires-Dist: mkdocs-material ; extra == 'develop'
Requires-Dist: mkdocstrings[python] ; extra == 'develop'
Requires-Dist: mkdocs-gen-files ; extra == 'develop'
Requires-Dist: mkdocs-literate-nav ; extra == 'develop'
Requires-Dist: mkdocs-section-index ; extra == 'develop'
Requires-Dist: mkdocs-jupyter ; extra == 'develop'
Provides-Extra: profiling
Requires-Dist: py-spy ; extra == 'profiling'
